README
setup.py
pyquickenv/__init__.py
pyquickenv/__main__.py
pyquickenv.egg-info/PKG-INFO
pyquickenv.egg-info/SOURCES.txt
pyquickenv.egg-info/dependency_links.txt
pyquickenv.egg-info/entry_points.txt
pyquickenv.egg-info/top_level.txt