Metadata-Version: 1.0
Name: pyquickenv
Version: 1.0.3
Summary: A command line tool to start Python virtual environments faster and easier.
Home-page: https://github.com/pizzapanther/Python-Quick-Env
Author: Paul Bailey
Author-email: paul.m.bailey@gmail.com
License: BSD
Platform: UNKNOWN
